fasttests/__init__.py
fasttests/main.py
fasttests-0.1.4.dist-info/METADATA
fasttests-0.1.4.dist-info/WHEEL
fasttests-0.1.4.dist-info/top_level.txt
fasttests-0.1.4.dist-info/RECORD
