Metadata-Version: 2.4
Name: fasttests
Version: 0.1.4
Summary: library for generating automated test templates
Author-email: Alexander Tomonov <tomonow.a@yandex.ru>
License: MIT
Requires-Python: >=3.12
